atomic_physics/__init__.py
atomic_physics/atoms/__init__.py
atomic_physics/atoms/two_state.py
atomic_physics/core.py
atomic_physics/examples/M1_transitions.py
atomic_physics/examples/__init__.py
atomic_physics/examples/breit_rabi.py
atomic_physics/examples/ca_shelving.py
atomic_physics/examples/clock_qubits.py
atomic_physics/ions/__init__.py
atomic_physics/ions/ba133.py
atomic_physics/ions/ba135.py
atomic_physics/ions/ba137.py
atomic_physics/ions/ba138.py
atomic_physics/ions/ca40.py
atomic_physics/ions/ca43.py
atomic_physics/ions/mg25.py
atomic_physics/ions/sr88.py
atomic_physics/operators.py
atomic_physics/polarization.py
atomic_physics/rate_equations.py
atomic_physics/tests/__init__.py
atomic_physics/tests/test_atom.py
atomic_physics/tests/test_atom_factory.py
atomic_physics/tests/test_atoms.py
atomic_physics/tests/test_ca43.py
atomic_physics/tests/test_examples.py
atomic_physics/tests/test_level_data.py
atomic_physics/tests/test_mg25.py
atomic_physics/tests/test_operators.py
atomic_physics/tests/test_polarization.py
atomic_physics/tests/test_rates.py
atomic_physics/tests/test_spin_half.py
atomic_physics/tests/test_spont.py
atomic_physics/tests/test_stim.py
atomic_physics/tests/test_two_state_atom.py
atomic_physics/tests/test_utils.py
atomic_physics/tests/test_wigner.py
atomic_physics/tests/utils.py
atomic_physics/utils.py
atomic_physics/wigner.py
atomic_physics-2.0.5.dist-info/METADATA
atomic_physics-2.0.5.dist-info/WHEEL
atomic_physics-2.0.5.dist-info/RECORD
